{
  "generatedAt": "2026-02-19T20:20:20+00:00",
  "modules": {
    "nkla_recent_10k_10q": {
      "provenance": {
        "asOf": "2025-10-09",
        "fetchedAt": "2026-02-19T20:20:24+00:00",
        "note": "10-K/10-Q count in last 365d",
        "source": "sec:0001731289"
      },
      "status": "ok"
    },
    "spy_30d_return": {
      "provenance": {
        "asOf": "2026-02-19",
        "fetchedAt": "2026-02-19T20:20:20+00:00",
        "note": "30d total return",
        "source": "stooq:SPY"
      },
      "status": "ok"
    }
  },
  "overallStatus": "ok",
  "policyDecision": "Strict real-feed mode with stale-real cache continuity.",
  "policyMode": "strict-real",
  "runId": "real-20260219202020"
}
